zabbix_exporter/__init__.py
zabbix_exporter/commands.py
zabbix_exporter/compat.py
zabbix_exporter/core.py
zabbix_exporter/prometheus.py
zabbix_exporter/utils.py
zabbix_exporter-1.0.2.dist-info/DESCRIPTION.rst
zabbix_exporter-1.0.2.dist-info/METADATA
zabbix_exporter-1.0.2.dist-info/RECORD
zabbix_exporter-1.0.2.dist-info/WHEEL
zabbix_exporter-1.0.2.dist-info/entry_points.txt
zabbix_exporter-1.0.2.dist-info/metadata.json
zabbix_exporter-1.0.2.dist-info/top_level.txt
