Metadata-Version: 2.0
Name: zabbix-exporter
Version: 1.0.2
Summary: zabbix metrics for Prometheus
Home-page: https://github.com/MyBook/zabbix-exporter
Author: MyBook
Author-email: coagulant@mybook.ru
License: BSD
Keywords: zabbix_exporter
Platform: UNKNOWN
Classifier: Development Status :: 5 - Production/Stable
Classifier: Intended Audience :: Developers
Classifier: License :: OSI Approved :: BSD License
Classifier: Natural Language :: English
Classifier: Programming Language :: Python :: 2
Classifier: Programming Language :: Python :: 2.7
Classifier: Programming Language :: Python :: 3
Classifier: Programming Language :: Python :: 3.5
Classifier: Programming Language :: Python :: 3.6
Classifier: Programming Language :: Python :: Implementation :: CPython
Classifier: Programming Language :: Python :: Implementation :: PyPy
Requires-Dist: PyYAML (>=3.11)
Requires-Dist: click (>=6.4)
Requires-Dist: prometheus-client (>=0.0.13)
Requires-Dist: pyzabbix (>=0.7.4)
